gitlabform/__init__.py
gitlabform/constants.py
gitlabform/output.py
gitlabform/run.py
gitlabform/util.py
gitlabform/configuration/__init__.py
gitlabform/configuration/common.py
gitlabform/configuration/core.py
gitlabform/configuration/groups.py
gitlabform/configuration/projects.py
gitlabform/configuration/transform.py
gitlabform/gitlab/__init__.py
gitlabform/gitlab/commits.py
gitlabform/gitlab/core.py
gitlabform/gitlab/group_badges.py
gitlabform/gitlab/group_ldap_links.py
gitlabform/gitlab/group_variables.py
gitlabform/gitlab/groups.py
gitlabform/gitlab/merge_requests.py
gitlabform/gitlab/pipelines.py
gitlabform/gitlab/project_badges.py
gitlabform/gitlab/project_deploy_keys.py
gitlabform/gitlab/project_merge_requests_approvals.py
gitlabform/gitlab/project_protected_environments.py
gitlabform/gitlab/project_security_settings.py
gitlabform/gitlab/projects.py
gitlabform/gitlab/python_gitlab.py
gitlabform/gitlab/variables.py
gitlabform/lists/__init__.py
gitlabform/lists/filter.py
gitlabform/lists/groups.py
gitlabform/lists/projects.py
gitlabform/processors/__init__.py
gitlabform/processors/abstract_processor.py
gitlabform/processors/defining_keys.py
gitlabform/processors/multiple_entities_processor.py
gitlabform/processors/single_entity_processor.py
gitlabform/processors/application/__init__.py
gitlabform/processors/application/application_settings_processor.py
gitlabform/processors/group/__init__.py
gitlabform/processors/group/group_badges_processor.py
gitlabform/processors/group/group_hooks_processor.py
gitlabform/processors/group/group_labels_processor.py
gitlabform/processors/group/group_ldap_links_processor.py
gitlabform/processors/group/group_members_processor.py
gitlabform/processors/group/group_push_rules_processor.py
gitlabform/processors/group/group_saml_links_processor.py
gitlabform/processors/group/group_settings_processor.py
gitlabform/processors/group/group_variables_processor.py
gitlabform/processors/project/__init__.py
gitlabform-4.7.0.dist-info/licenses/LICENSE
gitlabform-4.7.0.dist-info/METADATA
gitlabform-4.7.0.dist-info/WHEEL
gitlabform-4.7.0.dist-info/entry_points.txt
gitlabform-4.7.0.dist-info/top_level.txt
gitlabform-4.7.0.dist-info/RECORD
