Metadata-Version: 2.4
Name: gitlabform
Version: 4.7.0
Summary: 🏗 Specialized configuration as a code tool for GitLab projects, groups and more using hierarchical configuration written in YAML
Author: Greg Dubicki and Contributors
Project-URL: Homepage, https://gitlabform.github.io/gitlabform/
Project-URL: Repository, https://github.com/gitlabform/gitlabform.git
Project-URL: Issues, https://github.com/gitlabform/gitlabform/issues
Project-URL: Changelog, https://gitlabform.github.io/gitlabform/changelog/
Keywords: cli,yaml,gitlab,configuration-as-code
Classifier: Programming Language :: Python :: 3.12
Classifier: Development Status :: 5 - Production/Stable
Classifier: Intended Audience :: Information Technology
Classifier: Intended Audience :: System Administrators
Classifier: License :: OSI Approved :: MIT License
Classifier: Operating System :: POSIX :: Linux
Classifier: Operating System :: MacOS
Classifier: Operating System :: Microsoft :: Windows
Classifier: Topic :: Software Development :: Version Control :: Git
Requires-Python: >=3.12.0
License-File: LICENSE
Requires-Dist: certifi==2026.1.4
Requires-Dist: cli-ui==0.19.0
Requires-Dist: ez-yaml==1.2.0
Requires-Dist: Jinja2==3.1.6
Requires-Dist: luddite==1.0.4
Requires-Dist: MarkupSafe==3.0.3
Requires-Dist: mergedeep==1.3.4
Requires-Dist: packaging==25.0
Requires-Dist: python-gitlab==7.1.0
Requires-Dist: python-gitlab[graphql]==7.1.0
Requires-Dist: requests==2.32.5
Requires-Dist: ruamel.yaml==0.17.21
Requires-Dist: types-requests==2.32.4.20260107
Requires-Dist: types-setuptools==80.9.0.20251223
Requires-Dist: yamlpath==3.8.2
Provides-Extra: test
Requires-Dist: coverage==7.13.1; extra == "test"
Requires-Dist: cryptography==46.0.3; extra == "test"
Requires-Dist: deepdiff==8.6.1; extra == "test"
Requires-Dist: mypy==1.19.1; extra == "test"
Requires-Dist: mypy-extensions==1.1.0; extra == "test"
Requires-Dist: pre-commit==2.21.0; extra == "test"
Requires-Dist: pytest==9.0.2; extra == "test"
Requires-Dist: pytest-cov==7.0.0; extra == "test"
Requires-Dist: pytest-rerunfailures==16.1; extra == "test"
Requires-Dist: xkcdpass==1.30.0; extra == "test"
Provides-Extra: docs
Requires-Dist: mkdocs; extra == "docs"
Requires-Dist: mkdocs-material; extra == "docs"
Dynamic: license-file
